dw_yahoo_earnings_calendar-0.0.2.dist-info/METADATA
dw_yahoo_earnings_calendar-0.0.2.dist-info/RECORD
dw_yahoo_earnings_calendar-0.0.2.dist-info/WHEEL
dw_yahoo_earnings_calendar-0.0.2.dist-info/top_level.txt
yahoo_earnings_calendar/__init__.py
yahoo_earnings_calendar/scraper.py
