Metadata-Version: 2.1
Name: dw-yahoo-earnings-calendar
Version: 0.0.2
Summary: Scrapes data from Yahoo! Finance earnings calendar
Home-page: UNKNOWN
Author: Daniel Wang
Author-email: danielwpz@gmail.com
License: UNKNOWN
Keywords: stock,earnings,yahoo,scrape,finance
Platform: UNKNOWN
Requires-Dist: requests
